saying/__init__.py
saying/base.py
saying/resources.py
saying/util.py
saying-0.0.2.dist-info/LICENSE
saying-0.0.2.dist-info/METADATA
saying-0.0.2.dist-info/WHEEL
saying-0.0.2.dist-info/top_level.txt
saying-0.0.2.dist-info/RECORD
