Metadata-Version: 2.1
Name: saying
Version: 0.0.2
Summary: AI-enabled quotes search
Home-page: https://github.com/thorwhalen/saying
Author: Thor Whalen
License: mit
Platform: any
License-File: LICENSE
